CHANGELOG.rst
LICENSE.txt
MANIFEST.in
README.rst
setup.py
priceprop/__init__.py
priceprop/batch.py
priceprop/propagator.py
priceprop.egg-info/PKG-INFO
priceprop.egg-info/SOURCES.txt
priceprop.egg-info/dependency_links.txt
priceprop.egg-info/not-zip-safe
priceprop.egg-info/requires.txt
priceprop.egg-info/top_level.txt
tests/__init__.py
tests/test_propagator.py